intc/__init__.py
intc/config.py
intc/exceptions.py
intc/loader.py
intc/parser.py
intc/register.py
intc/share.py
intc/utils.py
intc/version.py
intc-0.1.1.dist-info/LICENSE
intc-0.1.1.dist-info/METADATA
intc-0.1.1.dist-info/WHEEL
intc-0.1.1.dist-info/top_level.txt
intc-0.1.1.dist-info/RECORD
