Metadata-Version: 2.1
Name: intc
Version: 0.1.1
Summary: intc: intelligent python config toolkit
Home-page: https://github.com/cstsunfu/intc
Author: cstsunfu
Author-email: cstsunfu@gmail.com
License: Apache Software License
Requires-Python: >=3.8
License-File: LICENSE
Requires-Dist: pytest >=7.0
Requires-Dist: attrs >=23.1
Requires-Dist: cattrs >=23.1
Requires-Dist: hjson >=3.0
Requires-Dist: pyyaml >=6.0
Requires-Dist: click >=8.0
Requires-Dist: platformdirs >=4.2.0
